pubsub_opentelemetry/__init__.py
pubsub_opentelemetry/publisher_decorator.py
pubsub_opentelemetry/pubsub_instrumentation_provider.py
pubsub_opentelemetry/subscriber_decorator.py
pubsub_opentelemetry/utils.py
pubsub_opentelemetry/version.py
opentelemetry_instrumentation_pubsub-0.0.1a9.dist-info/LICENCE
opentelemetry_instrumentation_pubsub-0.0.1a9.dist-info/METADATA
opentelemetry_instrumentation_pubsub-0.0.1a9.dist-info/WHEEL
opentelemetry_instrumentation_pubsub-0.0.1a9.dist-info/top_level.txt
opentelemetry_instrumentation_pubsub-0.0.1a9.dist-info/RECORD
